stenocaptioner/__init__.py
stenocaptioner/core.py
stenocaptioner/move_funcs.py
stenocaptioner/utils.py
stenocaptioner-0.3.1.dist-info/entry_points.txt
stenocaptioner-0.3.1.dist-info/LICENSE
stenocaptioner-0.3.1.dist-info/WHEEL
stenocaptioner-0.3.1.dist-info/METADATA
stenocaptioner-0.3.1.dist-info/RECORD
