Metadata-Version: 2.1
Name: stenocaptioner
Version: 0.3.1
Summary: 
License: MIT
Author: nekanat
Author-email: nekanat.stock@gmail.com
Requires-Python: >=3.9,<4.0
Classifier: License :: OSI Approved :: MIT License
Classifier: Programming Language :: Python :: 3
Classifier: Programming Language :: Python :: 3.9
Classifier: Programming Language :: Python :: 3.10
Classifier: Programming Language :: Python :: 3.11
Requires-Dist: ffmpeg-python (==0.2.0)
Requires-Dist: more-itertools (>=9.0.0,<10.0.0)
Requires-Dist: moviepy (>=1.0.3,<2.0.0)
Requires-Dist: numpy (>=1.23.5,<2.0.0)
Requires-Dist: scipy (>=1.9.3,<2.0.0)
Requires-Dist: torch (>=1.13.0,<2.0.0)
Requires-Dist: tqdm (>=4.64.1,<5.0.0)
Requires-Dist: transformers (>=4.25.1,<5.0.0)
Requires-Dist: youtube-dl (>=2021.12.17,<2022.0.0)
